tagstudio/resources/__init__.py
tagstudio/resources/icon.icns
tagstudio/resources/icon.ico
tagstudio/resources/icon.png
tagstudio/resources/qt/fonts/Oxanium-Bold.ttf
tagstudio/resources/qt/images/box_icon_empty_128 - Copy.png
tagstudio/resources/qt/images/box_icon_empty_128.png
tagstudio/resources/qt/images/box_icon_filled_128 - Copy.png
tagstudio/resources/qt/images/box_icon_filled_128.png
tagstudio/resources/qt/images/clipboard_icon_128.png
tagstudio/resources/qt/images/collation_icon_128.png
tagstudio/resources/qt/images/edit_icon_128.png
tagstudio/resources/qt/images/edit_icon_dark_128.png
tagstudio/resources/qt/images/pause.svg
tagstudio/resources/qt/images/play.svg
tagstudio/resources/qt/images/splash.png
tagstudio/resources/qt/images/splitter_handle_128.png
tagstudio/resources/qt/images/star_icon_empty_128 - Copy.png
tagstudio/resources/qt/images/star_icon_empty_128.png
tagstudio/resources/qt/images/star_icon_filled_128 - Copy.png
tagstudio/resources/qt/images/star_icon_filled_128.png
tagstudio/resources/qt/images/tag_group_icon_128.png
tagstudio/resources/qt/images/tag_group_icon_dark_128.png
tagstudio/resources/qt/images/tagstudio_logo_text_mono.png
tagstudio/resources/qt/images/thumb_border_512.png
tagstudio/resources/qt/images/thumb_broken_512.png
tagstudio/resources/qt/images/thumb_file_default_512.png
tagstudio/resources/qt/images/thumb_loading_512.png
tagstudio/resources/qt/images/thumb_loading_dark_512.png
tagstudio/resources/qt/images/thumb_mask_128.png
tagstudio/resources/qt/images/thumb_mask_512.png
tagstudio/resources/qt/images/thumb_mask_hl_512.png
tagstudio/resources/qt/images/trash_icon_128.png
tagstudio/resources/qt/images/trash_icon_dark_128.png
tagstudio/resources/qt/images/volume.svg
tagstudio/resources/qt/images/volume_mute.svg
tagstudio/src/core/constants.py
tagstudio/src/core/enums.py
tagstudio/src/core/field_template.py
tagstudio/src/core/json_typing.py
tagstudio/src/core/library.py
tagstudio/src/core/palette.py
tagstudio-9.1.1.dist-info/LICENSE
tagstudio-9.1.1.dist-info/METADATA
tagstudio-9.1.1.dist-info/WHEEL
tagstudio-9.1.1.dist-info/entry_points.txt
tagstudio-9.1.1.dist-info/RECORD
