Metadata-Version: 2.1
Name: tagstudio
Version: 9.1.1
Summary: TagStudio (Alpha): A User-Focused Document Management System TagStudio is a photo & file organization application with an underlying system that focuses on giving freedom and flexibility to the user. No proprietary programs or formats, no sea of sidecar files, and no complete upheaval of your filesystem structure.
Home-page: https://github.com/TagStudioDev/TagStudio
License: GPL-3.0-only
Author: Travis Abendshien
Requires-Python: >=3.12,<3.13
Classifier: License :: OSI Approved :: GNU General Public License v3 (GPLv3)
Classifier: Programming Language :: Python :: 3
Classifier: Programming Language :: Python :: 3.12
Requires-Dist: Pillow (==10.3.0)
Requires-Dist: PySide6 (==6.7.1)
Requires-Dist: PySide6_Addons (==6.7.1)
Requires-Dist: PySide6_Essentials (==6.7.1)
Requires-Dist: chardet (==5.2.0)
Requires-Dist: humanfriendly (==10.0)
Requires-Dist: numpy (==1.26.4)
Requires-Dist: opencv_python (>=4.8.0.74,<=4.9.0.80)
Requires-Dist: pillow-heif (==0.16.0)
Requires-Dist: rawpy (==0.21.0)
Requires-Dist: typing_extensions (>=3.10.0.0,<=4.11.0)
Requires-Dist: ujson (>=5.8.0,<=5.9.0)
Project-URL: Discord, https://discord.gg/hRNnVKhF2G
Project-URL: Repository, https://github.com/TagStudioDev/TagStudio
